shimoku/__init__.py
shimoku/async_execution_pool.py
shimoku/exceptions.py
shimoku/execution_logger.py
shimoku/utils.py
shimoku/actions_execution/execute_action.py
shimoku/actions_execution/front_connection.py
shimoku/ai/ai_layer.py
shimoku/ai/generated_headers/AILayerHeader.py
shimoku/api/base_resource.py
shimoku/api/client.py
shimoku/api/utils.py
shimoku/api/resources/action.py
shimoku/api/resources/action_template.py
shimoku/api/resources/activity.py
shimoku/api/resources/activity_template.py
shimoku/api/resources/app.py
shimoku/api/resources/business.py
shimoku/api/resources/business_user.py
shimoku/api/resources/dashboard.py
shimoku/api/resources/data_set.py
shimoku/api/resources/event.py
shimoku/api/resources/file.py
shimoku/api/resources/report.py
shimoku/api/resources/role.py
shimoku/api/resources/universe.py
shimoku/api/resources/reports/filter_data_set.py
shimoku/api/resources/reports/modal.py
shimoku/api/resources/reports/tabs_group.py
shimoku/api/resources/reports/unsupported.py
shimoku/api/resources/reports/charts/annotated_chart.py
shimoku/api/resources/reports/charts/button.py
shimoku/api/resources/reports/charts/echart.py
shimoku/api/resources/reports/charts/html.py
shimoku/api/resources/reports/charts/iframe.py
shimoku/api/resources/reports/charts/indicator.py
shimoku/api/resources/reports/charts/input_form.py
shimoku/api/resources/reports/charts/table.py
shimoku/api/user_access_classes/actions_layer.py
shimoku/api/user_access_classes/activities_layer.py
shimoku/api/user_access_classes/activity_templates_layer.py
shimoku/api/user_access_classes/apps_layer.py
shimoku/api/user_access_classes/businesses_layer.py
shimoku/api/user_access_classes/dashboards_layer.py
shimoku/api/user_access_classes/data_sets_layer.py
shimoku/api/user_access_classes/files_layer.py
shimoku/api/user_access_classes/reports_layer.py
shimoku/api/user_access_classes/universes_layer.py
shimoku/api/user_access_classes/generated_headers/ActionsLayerHeader.py
shimoku-2.6.4.dist-info/LICENSE.txt
shimoku-2.6.4.dist-info/METADATA
shimoku-2.6.4.dist-info/WHEEL
shimoku-2.6.4.dist-info/entry_points.txt
shimoku-2.6.4.dist-info/top_level.txt
shimoku-2.6.4.dist-info/RECORD
