Metadata-Version: 2.1
Name: shimoku
Version: 2.6.4
Summary: Shimoku enables you to build Data Products in just hours and allows you to create Predictive Analytics Products with Artificial Intelligence capabilities.
Home-page: https://github.com/shimoku-tech/shimoku-api-python
Author: Shimoku
Author-email: contact@shimoku.com
License: MIT
Project-URL: Documentation, https://docs.shimoku.com/
Platform: any
Classifier: Development Status :: 4 - Beta
Classifier: Programming Language :: Python
Requires-Python: >=3.9
License-File: LICENSE.txt
Requires-Dist: importlib-metadata
Requires-Dist: pandas >=2.2.2
Requires-Dist: shimoku-components-catalog >=0.2.1
Requires-Dist: json5 ~=0.9.10
Requires-Dist: requests ~=2.31.0
Requires-Dist: datetime ~=4.9
Requires-Dist: tqdm ~=4.64.1
Requires-Dist: psutil ~=5.9.4
Requires-Dist: aiohttp >=3.9.2
Requires-Dist: ipython >=8.10
Requires-Dist: uvicorn ~=0.23.2
Requires-Dist: graphene ~=3.3
Requires-Dist: urllib3 ~=1.26.13
Requires-Dist: pydantic ~=2.4.2
Requires-Dist: strawberry-graphql ~=0.198.0
Requires-Dist: starlette-graphene3 ~=0.6.0
Requires-Dist: fastapi >=0.109.1
Requires-Dist: websockets ~=11.0.3
Requires-Dist: python-dateutil ~=2.8.2
Requires-Dist: rich ~=13.7.0
Requires-Dist: black ~=23.11.0
Requires-Dist: deepdiff ~=6.7.1
Requires-Dist: psutil ~=5.9.7
Requires-Dist: watchdog ~=4.0.0
